ezcolorlog/__init__.py
ezcolorlog/config.py
ezcolorlog/defaults.yaml
ezcolorlog/format.py
ezcolorlog/logfile.py
ezcolorlog/notebook.py
ezcolorlog/patch.py
ezcolorlog/wrapper.py
EzColorLog-1.0.3.dist-info/LICENSE
EzColorLog-1.0.3.dist-info/METADATA
EzColorLog-1.0.3.dist-info/WHEEL
EzColorLog-1.0.3.dist-info/top_level.txt
EzColorLog-1.0.3.dist-info/RECORD
