Metadata-Version: 2.1
Name: EzColorLog
Version: 1.0.3
Summary: A simple pretty Python logging interface.
Author-email: Ellis Brown <ellis.l.brown.ii@gmail.com>
License: MIT License
Project-URL: Code, https://github.com/ellisbrown/EzColorLog
Project-URL: Issues, https://github.com/ellisbrown/EzColorLog/issues
Keywords: logging,color,easy,simple,pretty
Classifier: Programming Language :: Python :: 3 :: Only
Classifier: Programming Language :: Python :: 3.8
Classifier: Programming Language :: Python :: 3.9
Classifier: Programming Language :: Python :: 3.10
Classifier: Programming Language :: Python :: 3.11
Classifier: Programming Language :: Python :: 3.12
Classifier: Development Status :: 3 - Alpha
Classifier: Operating System :: OS Independent
Classifier: Topic :: Software Development :: Libraries :: Python Modules
Classifier: Intended Audience :: Developers
Classifier: Intended Audience :: Science/Research
Classifier: License :: OSI Approved :: MIT License
Requires-Python: >=3
License-File: LICENSE
Requires-Dist: coloredlogs
Requires-Dist: colorama
Requires-Dist: pyyaml
Requires-Dist: IPython
Provides-Extra: tqdm
Requires-Dist: tqdm ; extra == 'tqdm'
